plambda/__init__.py
plambda/version.py
plambda/actors/__init__.py
plambda/actors/actorlib.py
plambda/actors/console.py
plambda/actors/pyactor.py
plambda/antlr4/PLambdaLexer.py
plambda/antlr4/PLambdaListener.py
plambda/antlr4/PLambdaParser.py
plambda/antlr4/PLambdaVisitor.py
plambda/antlr4/__init__.py
plambda/eval/Closure.py
plambda/eval/Code.py
plambda/eval/Continuation.py
plambda/eval/Environment.py
plambda/eval/Flags.py
plambda/eval/Globals.py
plambda/eval/Interpreter.py
plambda/eval/PLambda.py
plambda/eval/PLambdaException.py
plambda/eval/State.py
plambda/eval/SymbolTable.py
plambda/eval/__init__.py
plambda/util/StringBuffer.py
plambda/util/Util.py
plambda/util/__init__.py
plambda/visitor/ParseError.py
plambda/visitor/Parser.py
plambda/visitor/Visitor.py
plambda/visitor/__init__.py
tests/drones/__init__.py
tests/drones/simple_drone.py
PLambda-1.1.1.dist-info/LICENSE
PLambda-1.1.1.dist-info/METADATA
PLambda-1.1.1.dist-info/WHEEL
PLambda-1.1.1.dist-info/entry_points.txt
PLambda-1.1.1.dist-info/top_level.txt
PLambda-1.1.1.dist-info/RECORD
