Metadata-Version: 2.1
Name: PLambda
Version: 1.1.1
Summary: The PLambda language
Home-page: https://github.com/SRI-CSL/PLambda
Author: Ian A. Mason
Author-email: iam@csl.sri.com
License: MIT
Platform: UNKNOWN
Classifier: Development Status :: 3 - Alpha
Classifier: Natural Language :: English
Classifier: Intended Audience :: Developers
Classifier: Topic :: System :: Distributed Computing
Classifier: License :: OSI Approved :: MIT License
Classifier: Operating System :: OS Independent
Classifier: Programming Language :: Python
Classifier: Programming Language :: Python :: 3
Classifier: Programming Language :: Python :: 3.5
Classifier: Programming Language :: Python :: 3.6
Classifier: Programming Language :: Python :: 3.7
Classifier: Programming Language :: Python :: 3.8
Requires-Dist: psutil (>=4.3.0)
Requires-Dist: antlr4-python3-runtime (>=4.8)
